pgformat/__init__.py
pgformat/__main__.py
pgformat/cli.py
pgformat/grammar.lark
pgformat/parser.py
pgformat/serializer.py
pgformat-0.2.1.dist-info/entry_points.txt
pgformat-0.2.1.dist-info/LICENSE
pgformat-0.2.1.dist-info/WHEEL
pgformat-0.2.1.dist-info/METADATA
pgformat-0.2.1.dist-info/RECORD
