Metadata-Version: 2.1
Name: pgformat
Version: 0.2.1
Summary: Property Graph Exchange Format (PG) parser and serializer
Author-email: Jakob Voß <jakob.voss@gbv.de>
Classifier: License :: OSI Approved :: MIT License
Requires-Dist: lark
Project-URL: Homepage, https://github.com/pg-format/pg-format-py
Project-URL: Issues, https://github.com/pg-format/pg-format-py/issues
